setup.py
UCI_Package/UCI_Package.py
UCI_Package.egg-info/PKG-INFO
UCI_Package.egg-info/SOURCES.txt
UCI_Package.egg-info/dependency_links.txt
UCI_Package.egg-info/top_level.txt